Metadata-Version: 2.4
Name: pyflow-workflow-generator
Version: 3.5.1
Summary: Create pythonic ecFlow suites
Author-email: "European Centre for Medium-Range Weather Forecasts (ECMWF)" <software.support@ecmwf.int>
Maintainer-email: Corentin Carton de Wiart <corentin.carton@ecmwf.int>
License:                                  Apache License
Project-URL: repository, https://github.com/ecmwf/pyflow
Project-URL: documentation, https://pyflow-workflow-generator.readthedocs.io
Project-URL: issues, https://github.com/ecmwf/pyflow/issues
Classifier: Development Status :: 4 - Beta
Classifier: Intended Audience :: Science/Research
Classifier: License :: OSI Approved :: Apache Software License
Classifier: Natural Language :: English
Classifier: Operating System :: OS Independent
Classifier: Programming Language :: Python :: 3
Classifier: Programming Language :: Python :: 3 :: Only
Classifier: Programming Language :: Python :: 3.8
Classifier: Programming Language :: Python :: 3.10
Classifier: Topic :: Scientific/Engineering
Requires-Python: >=3.8
License-File: LICENSE
Requires-Dist: jinja2
Requires-Dist: requests
Provides-Extra: test
Requires-Dist: pytest; extra == "test"
Provides-Extra: diagrams
Requires-Dist: graphviz; extra == "diagrams"
Dynamic: license-file
